MANIFEST.in
README.md
setup.py
coucou_lib/__init__.py
coucou_lib/coucou_lib.py
coucou_lib.egg-info/PKG-INFO
coucou_lib.egg-info/SOURCES.txt
coucou_lib.egg-info/dependency_links.txt
coucou_lib.egg-info/top_level.txt