Metadata-Version: 1.1
Name: coucou-lib
Version: 0.0.7
Summary: Ecrit COUOCU
Home-page: UNKNOWN
Author: Natasha
Author-email: natasha@gmail.com
License: WTFPL
Platform: UNKNOWN
Classifier: Programming Language :: Python
Classifier: Development Status :: 1 - Planning
Classifier: License :: OSI Approved
Classifier: Natural Language :: French
Classifier: Operating System :: OS Independent
Classifier: Programming Language :: Python :: 2.7
Classifier: Topic :: Communications
